{
  "sde": "vpsde",
  "sigma_min": 0.01,
  "sigma_max": 5.0,
  "beta_min": 0.1,
  "beta_max": 20.0,
  "ambient_dim": 64,
  "hidden_layers": 4,
  "hidden_nodes": 256,
  "model_name": "fcn",
  "epochs": 6000,
  "batch_size": 128,
  "lr": 0.0002,
  "ema_rate": 0.999,
  "weight_decay": 0.0,
  "warmup": 200,
  "likelihood_weighting": false,
  "reduce_mean": true,
  "continuous": true,
  "log_path": "/home/moritz.burmester/riemannian-score-metrics/experiments/model_logs",
  "log_name": "alphanum/vp_stdw"
}